Virec_publish/Common_function.py
Virec_publish/__init__.py
Virec_publish/configuration.py
virecfremwork-0.2.14.dist-info/LICENSE
virecfremwork-0.2.14.dist-info/METADATA
virecfremwork-0.2.14.dist-info/WHEEL
virecfremwork-0.2.14.dist-info/top_level.txt
virecfremwork-0.2.14.dist-info/RECORD
