Metadata-Version: 2.1
Name: VirecFremwork
Version: 0.2.14
Summary: Validate our data
Author: Sumit Zala
Author-email: sumit.zala@xbyte.io
License: MIT
Classifier: Programming Language :: Python :: 3
Classifier: License :: OSI Approved :: MIT License
Classifier: Operating System :: OS Independent
Requires-Python: >=3.7
License-File: LICENSE
Requires-Dist: requests
